{
"operatorDetails":[{
        "name":"yelahto",
        "data":"hjsdf sdfh skjdf"
     },
     {
        "name":"rect2",
        "data":"s sdfsdf f2"
     },
     {
        "name":"rect3",
        "data":"s sdfsdf f3"
     },
    {
        "name":"rect4",
        "data":"s sdfsdf f4"
     },
    {
        "name":"rect5",
        "data":"s sdfsdf f5"
     },
    {
        "name":"rect6",
        "data":"s sdfsdf f6"
     },
    {
        "name":"rect7",
        "data":"s sdfsdf f7"
     },
    {
        "name":"rect8",
        "data":"s sdfsdf f8"
     },
    {
        "name":"rect9",
        "data":"s sdfsdf f9"
     },
    {
        "name":"rect10",
        "data":"s sdfsdf f10"
     }]
}